pnk/__init__.py
pnk/__main__.py
pnk/core.py
pnk/helpers/__init__.py
pnk/helpers/logger.py
pnk/helpers/profiler.py
tests/__init__.py
tests/core_test.py
pnk-3.0.0.dist-info/LICENSE
pnk-3.0.0.dist-info/METADATA
pnk-3.0.0.dist-info/WHEEL
pnk-3.0.0.dist-info/entry_points.txt
pnk-3.0.0.dist-info/top_level.txt
pnk-3.0.0.dist-info/RECORD
