Metadata-Version: 2.1
Name: pnk
Version: 3.0.0
Summary: Generates permutations on provided subdomains
Author-email: Zhdanov Kirill <storenth@yandex.ru>
Project-URL: Homepage, https://github.com/storenth/pnk
Project-URL: Issues, https://github.com/storenth/pnk/issues
Keywords: permutations,enumeration,recon,itertool,subdomains,bugbounty,subdomain-enumeration,infosec
Classifier: Programming Language :: Python :: 3
Classifier: License :: OSI Approved :: MIT License
Classifier: Operating System :: OS Independent
Requires-Python: >=3.8
License-File: LICENSE
